CNVoyant/__init__.py
CNVoyant/classifier/__init__.py
CNVoyant/classifier/classifier.py
CNVoyant/classifier/models/scalers.pickle
CNVoyant/data/exons.bed.gz
CNVoyant/data/gene_positions.csv
CNVoyant/data/gnomad4.bed.gz
CNVoyant/data/hi_ts_regions.csv
CNVoyant/data/reg_regions.bed
CNVoyant/dependency_builder/__init__.py
CNVoyant/dependency_builder/dependency_builder.py
CNVoyant/explainer/__init__.py
CNVoyant/explainer/explainer.py
CNVoyant/feature_builder/__init__.py
CNVoyant/feature_builder/feature_builder.py
CNVoyant/liftover/__init__.py
CNVoyant/liftover/liftover.py
CNVoyant/liftover/paths.json
CNVoyant/liftover/src/hg19ToHg38.over.chain.gz
CNVoyant/liftover/src/liftover
CNVoyant-1.1.6.dist-info/LICENSE
CNVoyant-1.1.6.dist-info/METADATA
CNVoyant-1.1.6.dist-info/WHEEL
CNVoyant-1.1.6.dist-info/top_level.txt
CNVoyant-1.1.6.dist-info/RECORD
